Metadata-Version: 1.0
Name: nd-distriProb
Version: 1.1
Summary: Gaussian and Binomial distributions
Home-page: UNKNOWN
Author: Nancy Doss
Author-email: Nancyjaykujmar@hotmail.com
License: UNKNOWN
Platform: UNKNOWN
